{"name":"rfgd","fields":[{"totalRow":"10","totalCol":"4","fieldName":"set","ReadingDirection":"Vertical","allowMultiple":"false","fieldValue":"Integer","bubbleIntensity":17,"gap":"-11.8","x":53,"y":106,"width":45,"height":92,"bubbles":[{"x":116,"y":232,"width":24,"height":20,"row":0,"col":0},{"x":140,"y":232,"width":24,"height":20,"row":0,"col":1},{"x":165,"y":232,"width":24,"height":20,"row":0,"col":2},{"x":190,"y":232,"width":24,"height":20,"row":0,"col":3},{"x":116,"y":252,"width":24,"height":20,"row":1,"col":0},{"x":140,"y":252,"width":24,"height":20,"row":1,"col":1},{"x":165,"y":252,"width":24,"height":20,"row":1,"col":2},{"x":190,"y":252,"width":24,"height":20,"row":1,"col":3},{"x":116,"y":272,"width":24,"height":20,"row":2,"col":0},{"x":140,"y":272,"width":24,"height":20,"row":2,"col":1},{"x":165,"y":272,"width":24,"height":20,"row":2,"col":2},{"x":190,"y":272,"width":24,"height":20,"row":2,"col":3},{"x":116,"y":292,"width":24,"height":20,"row":3,"col":0},{"x":140,"y":292,"width":24,"height":20,"row":3,"col":1},{"x":165,"y":292,"width":24,"height":20,"row":3,"col":2},{"x":190,"y":292,"width":24,"height":20,"row":3,"col":3},{"x":116,"y":312,"width":24,"height":20,"row":4,"col":0},{"x":140,"y":312,"width":24,"height":20,"row":4,"col":1},{"x":165,"y":312,"width":24,"height":20,"row":4,"col":2},{"x":190,"y":312,"width":24,"height":20,"row":4,"col":3},{"x":116,"y":332,"width":24,"height":20,"row":5,"col":0},{"x":140,"y":332,"width":24,"height":20,"row":5,"col":1},{"x":165,"y":332,"width":24,"height":20,"row":5,"col":2},{"x":190,"y":332,"width":24,"height":20,"row":5,"col":3},{"x":116,"y":353,"width":24,"height":20,"row":6,"col":0},{"x":140,"y":353,"width":24,"height":20,"row":6,"col":1},{"x":165,"y":353,"width":24,"height":20,"row":6,"col":2},{"x":190,"y":353,"width":24,"height":20,"row":6,"col":3},{"x":116,"y":373,"width":24,"height":20,"row":7,"col":0},{"x":140,"y":373,"width":24,"height":20,"row":7,"col":1},{"x":165,"y":373,"width":24,"height":20,"row":7,"col":2},{"x":190,"y":373,"width":24,"height":20,"row":7,"col":3},{"x":116,"y":393,"width":24,"height":20,"row":8,"col":0},{"x":140,"y":393,"width":24,"height":20,"row":8,"col":1},{"x":165,"y":393,"width":24,"height":20,"row":8,"col":2},{"x":190,"y":393,"width":24,"height":20,"row":8,"col":3},{"x":116,"y":413,"width":24,"height":20,"row":9,"col":0},{"x":140,"y":413,"width":24,"height":20,"row":9,"col":1},{"x":165,"y":413,"width":24,"height":20,"row":9,"col":2},{"x":190,"y":413,"width":24,"height":20,"row":9,"col":3}],"fieldType":"formfield"},{"totalRow":"3","totalCol":"1","fieldName":"PC","fieldType":"formfield","ReadingDirection":"Vertical","allowMultiple":"false","fieldValue":"Integer","bubbleIntensity":7,"x":257,"y":125,"width":16,"height":48,"bubbles":[{"x":563,"y":273,"width":35,"height":35,"row":0,"col":0},{"x":563,"y":308,"width":35,"height":35,"row":1,"col":0},{"x":563,"y":343,"width":35,"height":35,"row":2,"col":0}]}]}