{"name":"tytrytr","fields":[{"totalRow":"10","totalCol":"4","fieldName":"roll","fieldType":"formfield","ReadingDirection":"Vertical","allowMultiple":"true","blankOuputSymbol":"-","fieldValue":"Integer","gap":"3","bubbleIntensity":6.7,"x":52,"y":109,"width":46,"height":90,"bubbles":[{"x":113,"y":238,"width":25,"height":19,"row":0,"col":0},{"x":139,"y":238,"width":25,"height":19,"row":0,"col":1},{"x":164,"y":238,"width":25,"height":19,"row":0,"col":2},{"x":189,"y":238,"width":25,"height":19,"row":0,"col":3},{"x":113,"y":258,"width":25,"height":19,"row":1,"col":0},{"x":139,"y":258,"width":25,"height":19,"row":1,"col":1},{"x":164,"y":258,"width":25,"height":19,"row":1,"col":2},{"x":189,"y":258,"width":25,"height":19,"row":1,"col":3},{"x":113,"y":278,"width":25,"height":19,"row":2,"col":0},{"x":139,"y":278,"width":25,"height":19,"row":2,"col":1},{"x":164,"y":278,"width":25,"height":19,"row":2,"col":2},{"x":189,"y":278,"width":25,"height":19,"row":2,"col":3},{"x":113,"y":297,"width":25,"height":19,"row":3,"col":0},{"x":139,"y":297,"width":25,"height":19,"row":3,"col":1},{"x":164,"y":297,"width":25,"height":19,"row":3,"col":2},{"x":189,"y":297,"width":25,"height":19,"row":3,"col":3},{"x":113,"y":317,"width":25,"height":19,"row":4,"col":0},{"x":139,"y":317,"width":25,"height":19,"row":4,"col":1},{"x":164,"y":317,"width":25,"height":19,"row":4,"col":2},{"x":189,"y":317,"width":25,"height":19,"row":4,"col":3},{"x":113,"y":337,"width":25,"height":19,"row":5,"col":0},{"x":139,"y":337,"width":25,"height":19,"row":5,"col":1},{"x":164,"y":337,"width":25,"height":19,"row":5,"col":2},{"x":189,"y":337,"width":25,"height":19,"row":5,"col":3},{"x":113,"y":357,"width":25,"height":19,"row":6,"col":0},{"x":139,"y":357,"width":25,"height":19,"row":6,"col":1},{"x":164,"y":357,"width":25,"height":19,"row":6,"col":2},{"x":189,"y":357,"width":25,"height":19,"row":6,"col":3},{"x":113,"y":376,"width":25,"height":19,"row":7,"col":0},{"x":139,"y":376,"width":25,"height":19,"row":7,"col":1},{"x":164,"y":376,"width":25,"height":19,"row":7,"col":2},{"x":189,"y":376,"width":25,"height":19,"row":7,"col":3},{"x":113,"y":396,"width":25,"height":19,"row":8,"col":0},{"x":139,"y":396,"width":25,"height":19,"row":8,"col":1},{"x":164,"y":396,"width":25,"height":19,"row":8,"col":2},{"x":189,"y":396,"width":25,"height":19,"row":8,"col":3},{"x":113,"y":416,"width":25,"height":19,"row":9,"col":0},{"x":139,"y":416,"width":25,"height":19,"row":9,"col":1},{"x":164,"y":416,"width":25,"height":19,"row":9,"col":2},{"x":189,"y":416,"width":25,"height":19,"row":9,"col":3}]}],"referncefield":[{"topLeft":{"x":81.0600706713781,"y":219.04761904761907,"width":60,"height":60},"topRight":{"x":308.904593639576,"y":219.04761904761907,"width":60,"height":60},"bottomLeft":{"x":81.0600706713781,"y":359.2380952380953,"width":60,"height":60},"bottomRight":{"x":308.904593639576,"y":359.2380952380953,"width":60,"height":60}}],"referenceCoordinate":{"width":104,"height":64,"x":37,"y":100}}